Repractise/README.md
Repractise/__init__.py
Repractise/__main__.py
Repractise/file.epub
Repractise/index.html
Repractise/css/__init__.py
Repractise/css/annotations.css
Repractise/css/main.css
Repractise/css/normalize.css
Repractise/css/popup.css
Repractise/font/__init__.py
Repractise/font/fontello.eot
Repractise/font/fontello.svg
Repractise/font/fontello.ttf
Repractise/font/fontello.woff
Repractise/img/__init__.py
Repractise/img/annotator-glyph-sprite.png
Repractise/img/annotator-icon-sprite.png
Repractise/img/apple-touch-icon.png
Repractise/img/cancelfullscreen.png
Repractise/img/close.png
Repractise/img/fullscreen.png
Repractise/img/loader.gif
Repractise/img/menu-icon.png
Repractise/img/save.png
Repractise/img/saved.png
Repractise/img/settings-s.png
Repractise/img/settings.png
Repractise/img/star.png
Repractise/js/__init__.py
Repractise/js/epub.js
Repractise/js/epub.min.js
Repractise/js/epub.min.map
Repractise/js/hooks.min.js
Repractise/js/hooks.min.map
Repractise/js/reader.js
Repractise/js/reader.js.map
Repractise/js/reader.min.js
Repractise/js/reader.min.map
Repractise/js/hooks/__init__.py
Repractise/js/hooks/extensions/__init__.py
Repractise/js/hooks/extensions/highlight.js
Repractise/js/libs/__init__.py
Repractise/js/libs/jquery.min.js
Repractise/js/libs/localforage.min.js
Repractise/js/libs/screenfull.js
Repractise/js/libs/screenfull.min.js
Repractise/js/libs/zip.min.js
Repractise/js/plugins/__init__.py
Repractise/js/plugins/hypothesis.js
Repractise/js/plugins/search.js
repractise-2024.3.2.0.dist-info/METADATA
repractise-2024.3.2.0.dist-info/WHEEL
repractise-2024.3.2.0.dist-info/entry_points.txt
repractise-2024.3.2.0.dist-info/top_level.txt
repractise-2024.3.2.0.dist-info/RECORD
